aavsoquery/__init__.py
aavsoquery/aavso_query.py
aavsoquery/plotter.py
aavsoquery-1.0.2.dist-info/licenses/LICENSE
aavsoquery-1.0.2.dist-info/METADATA
aavsoquery-1.0.2.dist-info/WHEEL
aavsoquery-1.0.2.dist-info/top_level.txt
aavsoquery-1.0.2.dist-info/RECORD
