Metadata-Version: 2.4
Name: aavsoquery
Version: 1.0.2
Summary: A Python module for fetching and plotting astronomical data of stars from AAVSO
Home-page: https://github.com/prashant050701/aavso_query
Author: Divyansh Srivastava
Author-email: divyansh@umk.pl
Classifier: Programming Language :: Python :: 3
Classifier: License :: OSI Approved :: MIT License
Classifier: Operating System :: OS Independent
License-File: LICENSE
Requires-Dist: requests
Requires-Dist: beautifulsoup4
Requires-Dist: numpy
Requires-Dist: matplotlib
Requires-Dist: lmfit
Dynamic: author
Dynamic: author-email
Dynamic: classifier
Dynamic: description
Dynamic: description-content-type
Dynamic: home-page
Dynamic: license-file
Dynamic: requires-dist
Dynamic: summary
